weixin_auto-3.9.11.17.dist-info/licenses/LICENSE
wxauto/__init__.py
wxauto/color.py
wxauto/elements.py
wxauto/errors.py
wxauto/languages.py
wxauto/uiautomation.py
wxauto/utils.py
wxauto/wxauto.py
weixin_auto-3.9.11.17.dist-info/METADATA
weixin_auto-3.9.11.17.dist-info/WHEEL
weixin_auto-3.9.11.17.dist-info/top_level.txt
weixin_auto-3.9.11.17.dist-info/RECORD
