Metadata-Version: 2.4
Name: weixin-auto
Version: 3.9.11.17
Summary: Windows版本微信客户端自动化，可实现简单的发送、接收微信消息、保存聊天图片
Home-page: https://github.com/cluic/wxauto
Author: cluic
Author-email: 
License: MIT
Classifier: Programming Language :: Python :: 3
Classifier: Operating System :: Microsoft :: Windows
Requires-Python: >=3.6
License-File: LICENSE
Requires-Dist: pywin32>=309
Requires-Dist: pillow>=11.1.0
Requires-Dist: psutil>=7.0.0
Requires-Dist: pyperclip>=1.9.0
Dynamic: author
Dynamic: classifier
Dynamic: description
Dynamic: description-content-type
Dynamic: home-page
Dynamic: license
Dynamic: license-file
Dynamic: requires-dist
Dynamic: requires-python
Dynamic: summary
